datasette_query_files/__init__.py
datasette_query_files-0.1.1.dist-info/LICENSE
datasette_query_files-0.1.1.dist-info/METADATA
datasette_query_files-0.1.1.dist-info/WHEEL
datasette_query_files-0.1.1.dist-info/entry_points.txt
datasette_query_files-0.1.1.dist-info/top_level.txt
datasette_query_files-0.1.1.dist-info/RECORD
