Metadata-Version: 2.1
Name: datasette-query-files
Version: 0.1.1
Summary: Write Datasette canned queries as plain SQL files
Home-page: https://github.com/eyeseast/datasette-query-files
Author: Chris Amico
License: Apache License, Version 2.0
Project-URL: Issues, https://github.com/eyeseast/datasette-query-files/issues
Project-URL: CI, https://github.com/eyeseast/datasette-query-files/actions
Project-URL: Changelog, https://github.com/eyeseast/datasette-query-files/releases
Classifier: Framework :: Datasette
Classifier: License :: OSI Approved :: Apache Software License
Requires-Python: >=3.7
License-File: LICENSE
Requires-Dist: datasette
Provides-Extra: test
Requires-Dist: pytest ; extra == 'test'
Requires-Dist: pytest-asyncio ; extra == 'test'
